swarmauri_certs_crlverifyservice/CrlVerifyService.py
swarmauri_certs_crlverifyservice/__init__.py
swarmauri_certs_crlverifyservice-0.1.0.dev4.dist-info/METADATA
swarmauri_certs_crlverifyservice-0.1.0.dev4.dist-info/WHEEL
swarmauri_certs_crlverifyservice-0.1.0.dev4.dist-info/entry_points.txt
swarmauri_certs_crlverifyservice-0.1.0.dev4.dist-info/RECORD
