Metadata-Version: 2.3
Name: swarmauri_certs_crlverifyservice
Version: 0.1.0.dev4
Summary: Certificate verification against CRLs
License: Apache-2.0
Author: Community Maintainer
Author-email: community@example.com
Requires-Python: >=3.10,<3.13
Classifier: License :: OSI Approved :: Apache Software License
Classifier: Programming Language :: Python :: 3.10
Classifier: Programming Language :: Python :: 3.11
Classifier: Programming Language :: Python :: 3.12
Requires-Dist: cryptography (>=41.0.0)
Requires-Dist: swarmauri-base
